assignment_app/__init__.py
assignment_app/assignment.py
assignment_app/model.py
assignment_app/query.py
assignment_app-0.0.3.dist-info/LICENSE
assignment_app-0.0.3.dist-info/METADATA
assignment_app-0.0.3.dist-info/WHEEL
assignment_app-0.0.3.dist-info/entry_points.txt
assignment_app-0.0.3.dist-info/top_level.txt
assignment_app-0.0.3.dist-info/RECORD
