Metadata-Version: 2.1
Name: assignment-app
Version: 0.0.3
Summary: demo python CLI tool to manage assignments
Home-page: https://github.com/Ofosu-Osei
Author: Ofosu Osei
License-File: LICENSE
Requires-Dist: attrs ==23.1.0
Requires-Dist: black ==22.3.0
Requires-Dist: click ==8.1.3
Requires-Dist: pytest ==7.1.3
Requires-Dist: rich ==13.6.0
Requires-Dist: ruff ==0.0.284
Requires-Dist: six ==1.16.0
Requires-Dist: tomli ==2.0.1
Requires-Dist: typer ==0.9.0
Requires-Dist: typing-extensions ==4.8.0
